cerf/__init__.py
cerf/compete.py
cerf/install_supplement.py
cerf/interconnect.py
cerf/lmp.py
cerf/logger.py
cerf/model.py
cerf/nov.py
cerf/outputs.py
cerf/package_data.py
cerf/process.py
cerf/process_region.py
cerf/read_config.py
cerf/stage.py
cerf/utils.py
cerf/data/README.md
cerf-2.4.0.dist-info/METADATA
cerf-2.4.0.dist-info/WHEEL
cerf-2.4.0.dist-info/licenses/LICENSE
cerf-2.4.0.dist-info/RECORD
