Metadata-Version: 2.3
Name: cerf
Version: 2.4.0
Summary: An open-source geospatial Python package for assessing and analyzing future electricity technology capacity expansion feasibility.
Project-URL: Repository, https://github.com/IMMM-SFA/cerf
Project-URL: Documentation, https://immm-sfa.github.io/cerf
Author-email: Chris Vernon <chris.vernon@pnnl.gov>, Kendall Mongird <kendall.mongird@pnnl.gov>, Nino Zuljevic <nino.zuljevic@pnnl.gov>
Maintainer-email: Chris Vernon <chris.vernon@pnnl.gov>, Kendall Mongird <kendall.mongird@pnnl.gov>
License: Copyright 2021 Battelle Memorial Institute
License-File: LICENSE
Classifier: Programming Language :: Python :: 3.9
Classifier: Programming Language :: Python :: 3.10
Classifier: Programming Language :: Python :: 3.11
Requires-Python: >=3.9
Requires-Dist: fiona>=1.8.19
Requires-Dist: geopandas>=0.9.0
Requires-Dist: joblib>=1.0.1
Requires-Dist: matplotlib>=3.3.3
Requires-Dist: numpy>=1.19.4
Requires-Dist: pandas>=1.1.4
Requires-Dist: pyarrow>=17.0.0
Requires-Dist: pyproj>=3.0.1
Requires-Dist: pyyaml>=5.4.1
Requires-Dist: rasterio>=1.2.3
Requires-Dist: requests>=2.25.1
Requires-Dist: rioxarray>=0.15
Requires-Dist: rtree>=0.9.7
Requires-Dist: scipy>=1.12
Requires-Dist: seaborn>=0.11.1
Requires-Dist: shapely>=1.7
Provides-Extra: deploy
Requires-Dist: twine>=4.0.1; extra == 'deploy'
Provides-Extra: docs
Requires-Dist: autodoc>=0.5.0; extra == 'docs'
Requires-Dist: build>=0.5.1; extra == 'docs'
Requires-Dist: ipykernel>=6.15.1; extra == 'docs'
Requires-Dist: nbsphinx~=0.8.6; extra == 'docs'
Requires-Dist: setuptools>=57.0.0; extra == 'docs'
Requires-Dist: sphinx-design~=0.5.0; extra == 'docs'
Requires-Dist: sphinx-mathjax-offline~=0.0.2; extra == 'docs'
Requires-Dist: sphinx-panels>=0.6.0; extra == 'docs'
Requires-Dist: sphinx-rtd-theme~=2.0.0; extra == 'docs'
Requires-Dist: sphinx~=7.2.6; extra == 'docs'
Provides-Extra: test
Requires-Dist: pytest-cov>=2.12.1; extra == 'test'
Requires-Dist: pytest>=6.0; extra == 'test'
